flowhash/.gitignore
flowhash/__init__.py
flowhash/flowhash.py
flowhash-1.0.1.dist-info/LICENSE
flowhash-1.0.1.dist-info/WHEEL
flowhash-1.0.1.dist-info/METADATA
flowhash-1.0.1.dist-info/RECORD
