Metadata-Version: 2.1
Name: flowhash
Version: 1.0.1
Summary: Proof of Concept: Generic python3 hashing algorythm where the input is executed as control flow instructions.
Author-email: Violet Emmott <violet.emmott@gmail.com>
Classifier: License :: OSI Approved :: MIT License
Classifier: Programming Language :: Python :: 3.10
Project-URL: Home, https://github.com/VyeFox/flowhash
